lxcible/__init__.py
lxcible/cli.py
lxcible/lxcible.py
lxcible-0.2.0.dist-info/LICENSE
lxcible-0.2.0.dist-info/METADATA
lxcible-0.2.0.dist-info/WHEEL
lxcible-0.2.0.dist-info/entry_points.txt
lxcible-0.2.0.dist-info/top_level.txt
lxcible-0.2.0.dist-info/RECORD
