Metadata-Version: 2.1
Name: lxcible
Version: 0.2.0
Summary: A dynamic Ansible inventory based on running linuxcontainers
Home-page: https://gitlab.science.ru.nl/bram/lxcible
Author: Bram Daams
Author-email: b.daams@science.ru.nl
License: GNU General Public License v3
Keywords: lxcible
Platform: UNKNOWN
Classifier: Development Status :: 2 - Pre-Alpha
Classifier: Intended Audience :: Developers
Classifier: License :: OSI Approved :: GNU General Public License v3 (GPLv3)
Classifier: Natural Language :: English
Classifier: Programming Language :: Python :: 3
Classifier: Programming Language :: Python :: 3.5
Classifier: Programming Language :: Python :: 3.6
Classifier: Programming Language :: Python :: 3.7
Classifier: Programming Language :: Python :: 3.8
Requires-Python: >=3.5
Requires-Dist: Click (>=7.0)
Requires-Dist: jq (>=1.0.2)
